mcp_trello/__init__.py
mcp_trello/server.py
mcp_trello-0.0.2.dist-info/METADATA
mcp_trello-0.0.2.dist-info/WHEEL
mcp_trello-0.0.2.dist-info/entry_points.txt
mcp_trello-0.0.2.dist-info/top_level.txt
mcp_trello-0.0.2.dist-info/RECORD
